{
  "id": "works",
  "endpoint": {
    "url": "http://ldf.fi/mmm/sparql",
    "useAuth": false,
    "prefixesFile": "SparqlQueriesPrefixes.js"
  },
  "sparqlQueriesFile": "SparqlQueriesPerspective1.js",
  "baseURI": "http://ldf.fi/mmm",
  "URITemplate": "<BASE_URI>/work/<LOCAL_ID>",
  "resultClasses": {
    "works": {
      "instanceConfig": {
        "propertiesQueryBlock": "workProperties",
        "instancePageResultClasses": {
          "instancePageTable": {
            "tabID": 0,
            "component": "InstancePageTable",
            "tabPath": "table",
            "tabIcon": "CalendarViewDay"
          },
          "instancePageExport": {
            "tabID": 1,
            "component": "Export",
            "tabPath": "export",
            "tabIcon": "CloudDownload",
            "pageType": "instancePage"
          }
        }
      }
    }
  },
  "properties": [
    {
      "id": "uri",
      "valueType": "object",
      "makeLink": true,
      "externalLink": true,
      "sortValues": true,
      "numberedList": false,
      "onlyOnInstancePage": true
    },
    {
      "id": "prefLabel",
      "valueType": "object",
      "makeLink": true,
      "externalLink": false,
      "sortValues": true,
      "numberedList": false,
      "minWidth": 250
    },
    {
      "id": "author",
      "valueType": "object",
      "makeLink": true,
      "externalLink": false,
      "sortValues": true,
      "numberedList": false,
      "minWidth": 250
    },
    {
      "id": "language",
      "valueType": "object",
      "makeLink": true,
      "externalLink": true,
      "sortValues": true,
      "numberedList": false,
      "minWidth": 150
    },
    {
      "id": "expression",
      "valueType": "object",
      "makeLink": true,
      "externalLink": false,
      "sortValues": true,
      "numberedList": false,
      "minWidth": 150,
      "onlyOnInstancePage": true
    },
    {
      "id": "manuscript",
      "valueType": "object",
      "makeLink": true,
      "externalLink": false,
      "sortValues": true,
      "numberedList": false,
      "minWidth": 250
    },
    {
      "id": "productionTimespan",
      "valueType": "object",
      "makeLink": false,
      "externalLink": false,
      "sortValues": true,
      "numberedList": false,
      "minWidth": 250
    },
    {
      "id": "collection",
      "valueType": "object",
      "makeLink": true,
      "externalLink": false,
      "sortValues": true,
      "numberedList": false,
      "minWidth": 200
    },
    {
      "id": "source",
      "valueType": "object",
      "makeLink": true,
      "externalLink": true,
      "sortValues": true,
      "numberedList": false,
      "minWidth": 200
    }
  ]
}